{
  "schema": "beamprop-air-table-v1",
  "generated": "2026-07-17T08:25:08+00:00",
  "properties": [
    "rho",
    "cp",
    "kappa_t",
    "n_minus_1"
  ],
  "units": [
    "kg/m^3",
    "J/(kg K)",
    "W/(m K)",
    "1"
  ],
  "shape": [
    4,
    101,
    29
  ],
  "T_axis_K": {
    "min": 200.0,
    "max": 400.0,
    "step": 2.0
  },
  "p_axis_Pa": {
    "min": 40000.0,
    "max": 110000.0,
    "step": 2500.0
  },
  "interpolation": "bilinear",
  "composition_mole_fractions": {
    "N2": 0.7811,
    "O2": 0.2096,
    "Ar": 0.0093
  },
  "molar_mass_kg_per_mol": 0.0289600326,
  "refractivity": {
    "lambda_ref_um": 1.0,
    "model": "Ciddor 1996 standard dry-air dispersion, density-scaled (Gladstone-Dale)",
    "n_minus_1_standard": 0.0002741661312146662,
    "rho_standard_kg_m3": 1.2247934349973137
  },
  "sources": {
    "rho_cp": "Mutation++ N2/O2/Ar equilibrium, cross-checked vs ideal gas + NASA-9 (McBride 2002)",
    "kappa_t": "Sutherland-form fit, spot-checked vs Lemmon 2004",
    "n_minus_1": "Ciddor 1996 at lambda_ref, scaled by rho"
  },
  "gates": {
    "max_rel_dev_rho": 1.145739808006141e-05,
    "max_rel_dev_cp": 0.0014336848301123029,
    "max_rel_dev_kappa_vs_nist": 0.010520017847831343
  },
  "provenance": {
    "script": "scripts/make_air_table.py",
    "beamprop_git": "c794e95-dirty",
    "python": "3.10.20",
    "platform": "macOS-26.5.2-arm64-arm-64bit",
    "mutationpp": {
      "package_version": "1.1.3",
      "module_path": "/opt/homebrew/lib/python3.10/site-packages/mutationpp/__init__.py",
      "data_directory": "/Users/giuseppe/Documents/Libraries/Mutationpp/data",
      "local_build_git": "v1.0.5-65-g56deaaa-dirty"
    }
  }
}
